[
  {
    "proyectoNombre": "Plataforma de E-Learning",
    "nombre": "Diseño de base de datos",
    "horasEstimadas": 10,
    "horasRegistradas": 2,
    "empleadosAsignados": [
      "carolina.silva@codesolutions.com",
      "natalia.perez@codesolutions.com"
    ],
    "fechaCreacion": "2025-09-16T09:05:00.000Z",
    "estado": "Pendiente"
  },
  {
    "proyectoNombre": "Sistema de Reservas Hotel",
    "nombre": "Implementar login y autenticación",
    "horasEstimadas": 8,
    "horasRegistradas": 0,
    "empleadosAsignados": [],
    "estado": "Pendiente",
    "fechaCreacion": "2025-09-16T09:35:00.000Z"
  },
  {
    "proyectoNombre": "Dashboard de Ventas",
    "nombre": "Configuración de reportes de ventas",
    "horasEstimadas": 6,
    "horasRegistradas": 1,
    "empleadosAsignados": [
      "lucia.fernandez@codesolutions.com"
    ],
    "estado": "Pendiente",
    "fechaCreacion": "2025-09-16T10:05:00.000Z"
  },
  {
    "proyectoNombre": "Plataforma de E-Learning",
    "nombre": "Maquetación de interfaz",
    "horasEstimadas": 12,
    "horasRegistradas": 6,
    "empleadosAsignados": [
      "lucia.fernandez@codesolutions.com",
      "martin.rojas@codesolutions.com"
    ],
    "estado": "Pendiente",
    "fechaCreacion": "2025-09-16T09:15:00.000Z"
  },
  {
    "proyectoNombre": "Plataforma de E-Learning",
    "nombre": "Pruebas unitarias backend",
    "horasEstimadas": 8,
    "horasRegistradas": 7,
    "empleadosAsignados": [
      "martin.rojas@codesolutions.com"
    ],
    "estado": "En progreso",
    "fechaCreacion": "2025-09-16T09:20:00.000Z"
  },
  {
    "proyectoNombre": "Sistema de Facturación Online",
    "nombre": "Revisión",
    "horasEstimadas": 5,
    "horasRegistradas": 4,
    "empleadosAsignados": [
      "valentina.gomez@codesolutions.com"
    ],
    "estado": "Finalizado",
    "fechaCreacion": "2025-09-21T06:37:28.241Z"
  },
  {
    "proyectoNombre": "Sistema de Facturación Online",
    "nombre": "factura",
    "horasEstimadas": 3,
    "horasRegistradas": 0,
    "empleadosAsignados": [
      "sofia.ramirez@codesolutions.com"
    ],
    "estado": "En progreso",
    "fechaCreacion": "2025-09-21T06:46:43.640Z"
  }
]
